{"wordRank":9161,"headWord":"marvellous","content":{"word":{"wordHead":"marvellous","wordId":"Level8luan_2_9161","content":{"sentence":{"sentences":[{"sContent":"‘How was your holiday?’ ‘Marvellous!’","sCn":"“假期过得好吗？”“好极了！”"}],"desc":"例句"},"usphone":"'mɑrvələs","syno":{"synos":[{"pos":"adj","tran":"不可思议的；惊人的","hwds":[{"w":"tremendous"},{"w":"magic"},{"w":"mysterious"},{"w":"incredible"},{"w":"spectacular"}]}],"desc":"同近"},"ukphone":"'mɑːv(ə)ləs","ukspeech":"marvellous&type=1","star":0,"phone":"'mɑ:viləs","speech":"marvellous","usspeech":"marvellous&type=2","trans":[{"tranCn":"不可思议的；惊人的","descCn":"中释","pos":"adj"}]}}},"bookId":"Level8luan_2"}
