{"wordRank":8907,"headWord":"resignation","content":{"word":{"wordHead":"resignation","wordId":"Level8luan_2_8907","content":{"sentence":{"sentences":[{"sContent":"Illness forced his resignation.","sCn":"他不得不因病辞职。"},{"sContent":"Further resignations are expected later this week.","sCn":"本周后半周会有更多人辞职。"}],"desc":"例句"},"usphone":",rɛzɪɡ'neʃən","syno":{"synos":[{"pos":"n","tran":"辞职；放弃；辞职书；顺从","hwds":[{"w":"compliance"},{"w":"demission"}]}],"desc":"同近"},"ukphone":"rezɪg'neɪʃ(ə)n","ukspeech":"resignation&type=1","star":0,"phone":",reziɡ'neiʃən","speech":"resignation","relWord":{"rels":[{"pos":"adj","words":[{"hwd":"resigned","tran":" 顺从的；已辞职的；己放弃的"}]},{"pos":"adv","words":[{"hwd":"resignedly","tran":" 听从地；服从地"}]},{"pos":"n","words":[{"hwd":"resign","tran":" 辞去职务"}]},{"pos":"v","words":[{"hwd":"resigned","tran":" 辞职；顺从（resign的过去分词）"}]},{"pos":"vi","words":[{"hwd":"resign","tran":" 辞职"}]},{"pos":"vt","words":[{"hwd":"resign","tran":" 辞职；放弃；委托；使听从"}]}],"desc":"同根"},"usspeech":"resignation&type=2","trans":[{"tranCn":"辞职；放弃；辞职书；顺从","descOther":"英释","descCn":"中释","pos":"n","tranOther":"an occasion when you officially announce that you have decided to leave your job or an organization, or a written statement that says you will be leaving"}]}}},"bookId":"Level8luan_2"}
