{"wordRank":4671,"headWord":"unprincipled","content":{"word":{"wordHead":"unprincipled","wordId":"Level8luan_2_4671","content":{"sentence":{"sentences":[{"sContent":"It is a market where people can be very unprincipled and unpleasant.","sCn":"在这个市场人们可能很缺乏原则也很不友好。"}],"desc":"例句"},"usphone":"ʌn'prɪnsəpld","syno":{"synos":[{"pos":"adj","tran":"无原则的；不道德的，不正直的；不合人道的","hwds":[{"w":"wicked"},{"w":"immoral"}]}],"desc":"同近"},"ukphone":"ʌn'prɪnsɪp(ə)ld","ukspeech":"unprincipled&type=1","star":0,"phone":",ʌn'prinsəpld","speech":"unprincipled","usspeech":"unprincipled&type=2","trans":[{"tranCn":"无原则的；不道德的，不正直的；不合人道的","descOther":"英释","descCn":"中释","pos":"adj","tranOther":"not caring whether what you do is morally right"}]}}},"bookId":"Level8luan_2"}
