{"wordRank":2998,"headWord":"bravura","content":{"word":{"wordHead":"bravura","wordId":"GRE_2_2998","content":{"sentence":{"sentences":[{"sContent":"a bravura performance","sCn":"技艺高超的表演"}],"desc":"例句"},"usphone":"brə'vjʊrə","ukphone":"brə'v(j)ʊərə","ukspeech":"bravura&type=1","star":0,"phone":"brə'vjuərə","speech":"bravura","relWord":{"rels":[{"pos":"adv","words":[{"hwd":"bravely","tran":" 勇敢地；华丽地"}]}],"desc":"同根"},"usspeech":"bravura&type=2","trans":[{"tranCn":"大胜的尝试,勇气的举动(显示演奏家技艺的壮丽的乐段)","descCn":"中释","pos":"n"}]}}},"bookId":"GRE_2"}
