{"wordRank":2031,"headWord":"lineal","content":{"word":{"wordHead":"lineal","wordId":"GRE_2_2031","content":{"sentence":{"sentences":[{"sContent":"lineal descendants","sCn":"直系后代"}],"desc":"例句"},"usphone":"'lɪnɪəl","syno":{"synos":[{"pos":"adj","tran":"直系的；嫡系的；世袭的","hwds":[{"w":"direct"},{"w":"patrimonial"}]}],"desc":"同近"},"ukphone":"'lɪnɪəl","ukspeech":"lineal&type=1","star":0,"phone":"'liniəl","speech":"lineal","remMethod":{"val":" lim(线) + eal → 直系的","desc":"记忆"},"relWord":{"rels":[{"pos":"adv","words":[{"hwd":"lineally","tran":" 直系地；嫡系地"}]}],"desc":"同根"},"usspeech":"lineal&type=2","trans":[{"tranCn":"直系的, 正统的","descOther":"英释","descCn":"中释","pos":"adj","tranOther":"related directly to someone who lived a long time before you"}]}}},"bookId":"GRE_2"}
