{"wordRank":7129,"headWord":"lop","content":{"word":{"wordHead":"lop","wordId":"GRE_2_7129","content":{"usphone":"lɑp","syno":{"synos":[{"pos":"vt","tran":"砍伐；剪去树枝","hwds":[{"w":"fell"}]},{"pos":"vi","tran":"砍，删；闲荡；下垂","hwds":[{"w":"moon"},{"w":"muck about"}]}],"desc":"同近"},"ukphone":"lɒp","ukspeech":"lop&type=1","star":0,"phrase":{"phrases":[{"pContent":"lop off","pCn":"砍掉"}],"desc":"短语"},"phone":"lɔp","speech":"lop","relWord":{"rels":[{"pos":"n","words":[{"hwd":"lopper","tran":" 砍除器；斩波器；树剪"}]}],"desc":"同根"},"usspeech":"lop&type=2","trans":[{"tranCn":"修剪, 砍伐, 斩","descCn":"中释","pos":"v"}]}}},"bookId":"GRE_2"}
