{"wordRank":815,"headWord":"dilute","content":{"word":{"wordHead":"dilute","wordId":"GMAT_2_815","content":{"sentence":{"sentences":[{"sContent":"dilute hydrochloric acid","sCn":"稀盐酸"}],"desc":"例句"},"usphone":"daɪ'l(j)ut","syno":{"synos":[{"pos":"adj","tran":"稀释的；淡的","hwds":[{"w":"watery"},{"w":"attenuant"}]},{"pos":"vt","tran":"稀释；冲淡；削弱","hwds":[{"w":"break"},{"w":"deliquate"}]},{"pos":"vi","tran":"变稀薄；变淡","hwds":[{"w":"thin"}]}],"desc":"同近"},"ukphone":"daɪ'l(j)uːt; dɪ-","ukspeech":"dilute&type=1","star":0,"phrase":{"phrases":[{"pContent":"dilute solution","pCn":"[化]稀溶液"},{"pContent":"dilute acid","pCn":"稀酸"},{"pContent":"dilute hydrochloric acid","pCn":"稀盐酸"},{"pContent":"dilute phase","pCn":"[化]稀相"},{"pContent":"dilute sulphuric acid","pCn":"稀硫酸"},{"pContent":"dilute with","pCn":"用…冲淡；用…稀释"}],"desc":"短语"},"phone":"dai'lju:t, di-","speech":"dilute","relWord":{"rels":[{"pos":"adj","words":[{"hwd":"diluted","tran":" 稀释的；无力的"},{"hwd":"diluent","tran":" 稀释的；冲淡的"}]},{"pos":"n","words":[{"hwd":"dilution","tran":" 稀释，冲淡；稀释法；冲淡物"},{"hwd":"diluent","tran":" 稀释液；冲淡剂"}]},{"pos":"v","words":[{"hwd":"diluted","tran":" 稀释（dilute的过去分词）；使减低（效果）"}]}],"desc":"同根"},"usspeech":"dilute&type=2","trans":[{"tranCn":"稀释的；淡的","descOther":"英释","descCn":"中释","pos":"adj","tranOther":"a dilute liquid has been made weaker by the addition of water or another liquid"},{"tranCn":"稀释；冲淡；削弱","descOther":"英释","descCn":"中释","pos":"v","tranOther":"to make a liquid weaker by adding water or another liquid"}]}}},"bookId":"GMAT_2"}
