{"wordRank":398,"headWord":"penalty","content":{"word":{"wordHead":"penalty","wordId":"CET6luan_1_398","content":{"sentence":{"sentences":[{"sContent":"No littering. Penalty $500.","sCn":"禁止乱扔垃圾。 违者罚款500美元。"},{"sContent":"Withdrawing the money early will result in a 10% penalty.","sCn":"提前支取这笔钱将被处以10%的罚金。"},{"sContent":"If he is convicted, he could receive the death penalty (= be killed as a punishment ) .","sCn":"一旦定罪，他可能会被判处死刑。"}],"desc":"例句"},"usphone":"'pɛnəlti","syno":{"synos":[{"pos":"n","tran":"[经]罚款，罚金；[法]处罚","hwds":[{"w":"fine"},{"w":"amercement"}]}],"desc":"同近"},"ukphone":"'penəltɪ","ukspeech":"penalty&type=1","star":0,"phrase":{"phrases":[{"pContent":"death penalty","pCn":"死刑"},{"pContent":"penalty function","pCn":"罚函数；[数]补偿函数"},{"pContent":"penalty for","pCn":"罚金；对…的处罚"},{"pContent":"administrative penalty","pCn":"行政处罚"},{"pContent":"penalty area","pCn":"罚球区，禁区"},{"pContent":"penalty kick","pCn":"罚点球，罚球"},{"pContent":"penalty spot","pCn":"罚球点"},{"pContent":"pay the penalty","pCn":"得报应，受惩罚"},{"pContent":"penalty factor","pCn":"惩罚因子"},{"pContent":"penalty shootout","pCn":"点球大战"},{"pContent":"penalty cost","pCn":"亏损；违约成本"},{"pContent":"penalty shot","pCn":"[篮]罚球；[冰]罚任意球"},{"pContent":"penalty goal","pCn":"罚球得分；罚进的球"},{"pContent":"penalty box","pCn":"（冰球、曲棍球）被罚下场的队员座席"}],"desc":"短语"},"phone":"'penəlti","speech":"penalty","relWord":{"desc":"同根","rels":[{"pos":"n","words":[{"hwd":"penalization","tran":"惩罚；处罚"}]},{"pos":"vt","words":[{"hwd":"penalize","tran":"处罚；处刑；使不利"},{"hwd":"penalise","tran":"惩罚，处罚；使…处于严重不利地位"}]}]},"usspeech":"penalty&type=2","trans":[{"tranCn":"惩罚","descOther":"英释","pos":"n","descCn":"中释","tranOther":"a punishment for breaking a law, rule, or legal agreement"}]}}},"bookId":"CET6luan_1"}
