{"wordRank":260,"headWord":"reluctant","content":{"word":{"wordHead":"reluctant","wordId":"BeiShiGaoZhong_9_260","content":{"sentence":{"sentences":[{"sContent":"She gave a reluctant smile.","sCn":"她勉强笑了笑。"}],"desc":"例句"},"usphone":"rɪ'lʌktənt","syno":{"synos":[{"pos":"adj","tran":"不情愿的；勉强的；顽抗的","hwds":[{"w":"narrow"},{"w":"unwilling"}]}],"desc":"同近"},"ukphone":"rɪ'lʌkt(ə)nt","ukspeech":"reluctant&type=1","phrase":{"phrases":[{"pContent":"reluctant to help","pCn":"不情愿帮忙"}],"desc":"短语"},"relWord":{"desc":"同根","rels":[{"pos":"adv","words":[{"hwd":"reluctantly","tran":" 不情愿地；嫌恶地"}]},{"pos":"n","words":[{"hwd":"reluctance","tran":" [电磁] 磁阻；勉强；不情愿"}]}]},"remMethod":{"val":" “驴拉坦克” → 真够勉强 → 勉强的","desc":"记忆"},"usspeech":"reluctant&type=2","trans":[{"tranCn":"勉强的，不愿意的","descOther":"英释","descCn":"中释","pos":"adj","tranOther":"slow and unwilling"}]}}},"bookId":"BeiShiGaoZhong_9"}
