{"wordRank":968,"headWord":"armored","content":{"word":{"wordHead":"armored","wordId":"GRE_3_968","content":{"sentence":{"sentences":[{"sContent":"Thee first \"standard\" battleship of the Tech Tree armored according to the \"all or nothing\" concept.","sContent_eng":"Thee first \"standard\" battleship of the Tech Tree <b>armored</b> according to the \"all or nothing\" concept.","sSpeech":"Thee+first+%22standard%22+battleship+of+the+Tech+Tree+armored+according+to+the+%22all+or+nothing%22+concept.&le=eng","sCn":"第一艘按照觨“全有或全没有”的理念进行装甲设计的标准级别战列舰。"},{"sContent":"When I see these articles I always remember the German Tiger 1 that attacked an entire armored column, alone.","sContent_eng":"When I see these articles I always remember the German Tiger 1 that attacked an entire <b>armored</b> column, alone.","sSpeech":"When+I+see+these+articles+I+always+remember+the+German+Tiger+1+that+attacked+an+entire+armored+column%2C+alone.&le=eng","sCn":"当我看到这类型的文章时，我总是会想起德国虎1坦克独自攻击整个装甲纵队的情景。"}],"desc":"例句"},"usphone":"'ɑrmɚd","syno":{"synos":[{"pos":"adj","tran":"装甲的","hwds":[{"w":"steel-clad"},{"w":"mailed"}]}],"desc":"同近"},"ukphone":"'ɑːrmərd","ukspeech":"armored&type=1","phrase":{"phrases":[{"pContent":"armored vehicle","pCn":"装甲车（辆）"},{"pContent":"armored concrete","pCn":"n. 钢筋混凝土；钢筋水泥"},{"pContent":"armored car","pCn":"n. 装甲车"},{"pContent":"armored forces","pCn":"n. 装甲部队"},{"pContent":"armored division","pCn":"n. 装甲师"}],"desc":"短语"},"relWord":{"rels":[{"pos":"adj","words":[{"hwd":"armed","tran":" 武装的；有扶手的；有防卫器官的（指动物）"}]},{"pos":"n","words":[{"hwd":"arm","tran":" 手臂；武器；袖子；装备"},{"hwd":"armor","tran":" [军] 装甲；盔甲"},{"hwd":"arming","tran":" 武装；装备；徽章"}]},{"pos":"vi","words":[{"hwd":"arm","tran":" 武装起来"}]},{"pos":"vt","words":[{"hwd":"arm","tran":" 武装；备战"},{"hwd":"armor","tran":" 为…装甲"}]}],"desc":"同根"},"usspeech":"armored&type=2","trans":[{"tranCn":" 披甲的， 装甲的","pos":"adj","descCn":"中释"}]}}},"bookId":"GRE_3"}
