{"wordRank":3309,"headWord":"bondage","content":{"word":{"wordHead":"bondage","wordId":"GRE_3_3309","content":{"sentence":{"sentences":[{"sContent":"the bondage of early motherhood","sCn":"刚刚做母亲时所受的束缚"}],"desc":"例句"},"usphone":"'bɑndɪdʒ","syno":{"synos":[{"pos":"n","tran":"奴役，束缚；奴役身份","hwds":[{"w":"chain"},{"w":"restriction"},{"w":"slavery"},{"w":"Enslaved"}]}],"desc":"同近"},"ukphone":"'bɑːndɪdʒ","ukspeech":"bondage&type=1","remMethod":{"val":" bond(使黏合) + age → 束缚","desc":"记忆"},"usspeech":"bondage&type=2","trans":[{"tranCn":" 奴役， 束缚","descOther":"英释","pos":"n","descCn":"中释","tranOther":"the state of having your freedom limited, or being prevented from doing what you want"}]}}},"bookId":"GRE_3"}
