{"wordRank":5775,"headWord":"comprehensively","content":{"word":{"wordHead":"comprehensively","wordId":"GRE_3_5775","content":{"usphone":",kɑmprɪ'hɛnsɪvli","ukphone":"ˌkɑːmprɪ'hensɪvli","ukspeech":"comprehensively&type=1","remMethod":{"val":" comprehen(=comprehend理解) + sive + ly → 完全理解地 → 全面地","desc":"记忆"},"relWord":{"rels":[{"pos":"adj","words":[{"hwd":"comprehensive","tran":" 综合的；广泛的；有理解力的"}]},{"pos":"n","words":[{"hwd":"comprehensive","tran":" 综合学校；专业综合测验"},{"hwd":"comprehension","tran":" 理解；包含"}]},{"pos":"vt","words":[{"hwd":"comprehend","tran":" 理解；包含；由…组成"}]}],"desc":"同根"},"usspeech":"comprehensively&type=2","trans":[{"tranCn":" 包括地； 全面地","pos":"adv","descCn":"中释"}]}}},"bookId":"GRE_3"}
