{"wordRank":3942,"headWord":"espy","content":{"word":{"wordHead":"espy","wordId":"GRE_3_3942","content":{"sentence":{"sentences":[{"sContent":"Here, from a window, did Guinevere espy a knight standing in a woodman's cart.","sCn":"吉尼维尔是从这里透过窗户看到了站在樵夫车上的骑士。"}],"desc":"例句"},"usphone":"i'spai","syno":{"synos":[{"pos":"vt","tran":"看到；认出；发现","hwds":[{"w":"detect"},{"w":"recognize"},{"w":"spot"}]}],"desc":"同近"},"ukphone":"e'spaɪ","ukspeech":"espy&type=1","remMethod":{"val":" e + spy(间谍， 发现) → 突然看到","desc":"记忆"},"usspeech":"espy&type=2","trans":[{"tranCn":" 突然看到； 望见","descOther":"英释","pos":"v","descCn":"中释","tranOther":"to suddenly see someone or something"}]}}},"bookId":"GRE_3"}
