{"wordRank":4307,"headWord":"slug","content":{"word":{"wordHead":"slug","wordId":"GRE_3_4307","content":{"usphone":"slʌɡ","syno":{"synos":[{"pos":"vi","tran":"偷懒；动作迟缓","hwds":[{"w":"spare oneself"},{"w":"slack off"}]},{"pos":"vt","tran":"重击","hwds":[{"w":"pound on"},{"w":"gang bang"}]}],"desc":"同近"},"ukphone":"slʌg","ukspeech":"slug&type=1","phrase":{"phrases":[{"pContent":"slug flow","pCn":"弹状流；活塞流"},{"pContent":"slug it out","pCn":"[美国口语] 决一雄雌"}],"desc":"短语"},"relWord":{"rels":[{"pos":"adj","words":[{"hwd":"sluggish","tran":" 萧条的；迟钝的；行动迟缓的；懒惰的"}]},{"pos":"n","words":[{"hwd":"sluggish","tran":" 市况呆滞；市势疲弱"},{"hwd":"slugger","tran":" 打击力强的选手；重击者"},{"hwd":"sluggishness","tran":" 迟缓；惰性；萧条"}]}],"desc":"同根"},"usspeech":"slug&type=2","trans":[{"tranCn":" 猛击， 拳击","descOther":"英释","pos":"v","descCn":"中释","tranOther":"to hit someone hard with your closed hand"}]}}},"bookId":"GRE_3"}
