{"wordRank":2028,"headWord":"sprout","content":{"word":{"wordHead":"sprout","wordId":"GRE_3_2028","content":{"sentence":{"sentences":[{"sContent":"Move the pots outside when the seeds begin to sprout.","sCn":"种子开始发芽时把盆搬到外面去。"},{"sContent":"Trees were starting to sprout new leaves.","sCn":"树上开始抽出新叶。"}],"desc":"例句"},"usphone":"spraʊt","syno":{"synos":[{"pos":"vi","tran":"发芽；长芽","hwds":[{"w":"put"},{"w":"come into bud"}]},{"pos":"vt","tran":"使发芽；使萌芽","hwds":[{"w":"germinate"},{"w":"bud"}]},{"pos":"n","tran":"[植]芽；萌芽；苗芽","hwds":[{"w":"seed"},{"w":"bud"}]}],"desc":"同近"},"ukphone":"spraut","ukspeech":"sprout&type=1","phrase":{"phrases":[{"pContent":"bean sprout","pCn":"豆芽"}],"desc":"短语"},"remMethod":{"val":" spr(看作spring) + out(出) → 春天来了， 嫩芽长出来了 → 长出， 萌芽","desc":"记忆"},"usspeech":"sprout&type=2","trans":[{"tranCn":"长出，萌芽","descOther":"英释","pos":"v","descCn":"中释","tranOther":"if vegetables, seeds, or plants sprout, they start to grow, producing  shoots  ,  buds  , or leaves"},{"tranCn":" 嫩芽","descOther":"英释","pos":"n","descCn":"中释","tranOther":"a small green vegetable like a very small  cabbage "}]}}},"bookId":"GRE_3"}
