{"wordRank":4178,"headWord":"unimpassioned","content":{"word":{"wordHead":"unimpassioned","wordId":"GRE_3_4178","content":{"usphone":"'ʌnim'pæʃənd","syno":{"synos":[{"pos":"adj","tran":"没有激情的；不动感情的；不感情用事的","hwds":[{"w":"unsentimental"},{"w":"hard-boiled"}]}],"desc":"同近"},"ukphone":"ˌʌnɪm'pæʃnd","ukspeech":"unimpassioned&type=1","remMethod":{"val":" un(不) + impassioned(充满激情的) → 没有激情的","desc":"记忆"},"usspeech":"unimpassioned&type=2","trans":[{"tranCn":" 没有激情的","pos":"adj","descCn":"中释"}]}}},"bookId":"GRE_3"}
