{"wordRank":677,"headWord":"fitting","content":{"word":{"wordHead":"fitting","wordId":"CET6_2_677","content":{"sentence":{"sentences":[{"sContent":"I thought the memorial was a fitting tribute to the President.","sCn":"我认为这座纪念碑恰如其分地表达了对总统的敬意。"},{"sContent":"new light fittings","sCn":"新款灯具配件"}],"desc":"例句"},"realExamSentence":{"sentences":[{"sContent":"...which have been high- profile in the past and reached a level of drama and theatrics fitting for a Las Vegas stage...","sourceInfo":{"paper":"第二套","level":"CET6","year":"2016.12","type":"阅读理解"}}],"desc":"真题例句"},"usphone":"'fɪtɪŋ","ukspeech":"fitting&type=1","star":0,"usspeech":"fitting&type=2","exam":[{"question":"Shoes of this kind are ______ to slip on wet ground.","answer":{"explain":" be apt to do： 易于， 倾向于。句意： 这种鞋在湿地上容易打滑。feasible： 可行的； appropriate： 适当的； fitting： 适合的， 恰当的。","rightIndex":3},"examType":1,"choices":[{"choiceIndex":1,"choice":"feasible"},{"choiceIndex":2,"choice":"appropriate"},{"choiceIndex":3,"choice":"apt"},{"choiceIndex":4,"choice":"fitting"}]}],"syno":{"synos":[{"pos":"n","tran":"[机]装配，装置；[服装]试穿，试衣","hwds":[{"w":"assembly"},{"w":"device"},{"w":"apparatus"},{"w":"installation"},{"w":"unit"}]},{"pos":"adj","tran":"适合的，适宜的；相称的","hwds":[{"w":"adaptive"},{"w":"calculated"},{"w":"matching"},{"w":"well"},{"w":"worthy"}]}],"desc":"同近"},"ukphone":"'fɪtɪŋ","phrase":{"phrases":[{"pContent":"curve fitting","pCn":"曲线拟合"},{"pContent":"pipe fitting","pCn":"管件；管道配件"},{"pContent":"data fitting","pCn":"数据拟合"},{"pContent":"fitting curve","pCn":"拟合曲线"},{"pContent":"fitting room","pCn":"服装店的试衣室；装配车间"},{"pContent":"hardware fitting","pCn":"五金配件"},{"pContent":"fitting out","pCn":"装配船只"},{"pContent":"fitting up","pCn":"组对，装配；初组装"},{"pContent":"least squares fitting","pCn":"最小二乘方拟合"},{"pContent":"lighting fitting","pCn":"灯具；照明配件；装灯配件"},{"pContent":"fitting surface","pCn":"配合面；安装面"},{"pContent":"fitting system","pCn":"[医]配镜器"}],"desc":"短语"},"phone":"'fitiŋ","speech":"fitting","relWord":{"desc":"同根","rels":[{"pos":"adj","words":[{"hwd":"fit","tran":"健康的；合适的；恰当的；准备好的"},{"hwd":"fitted","tran":"合适的；订做的；有…设备的"},{"hwd":"fitter","tran":"胜任的；适当的"}]},{"pos":"adv","words":[{"hwd":"fittingly","tran":"适切地，适合地"},{"hwd":"fitly","tran":"恰好地；适当地；整齐地"}]},{"pos":"n","words":[{"hwd":"fit","tran":"合身；发作；痉挛"},{"hwd":"fitness","tran":"健康；适当；适合性"},{"hwd":"fitter","tran":"装配工"},{"hwd":"fitment","tran":"家具；设备；配件（等于fittings）"}]},{"pos":"v","words":[{"hwd":"fitted","tran":"适应（fit的过去分词）；合适；为…提供设备"}]},{"pos":"vi","words":[{"hwd":"fit","tran":"符合，配合；适合；合身"}]},{"pos":"vt","words":[{"hwd":"fit","tran":"安装；使……适应；使……合身；与……相符"}]}]},"trans":[{"tranCn":"适当的","descOther":"英释","pos":"adj","descCn":"中释","tranOther":"right for a particular situation or occasion"},{"tranCn":"配件","descOther":"英释","pos":"n","descCn":"中释","tranOther":"an outside part of a piece of equipment that makes it possible to use or handle it"}]}}},"bookId":"CET6_2"}
