{"wordRank":1099,"headWord":"troublesome","content":{"word":{"wordHead":"troublesome","wordId":"CET6_2_1099","content":{"sentence":{"sentences":[{"sContent":"The economy has become a troublesome issue for the Conservative Party.","sCn":"经济状况已成为保守党的一大难题。"}],"desc":"例句"},"realExamSentence":{"sentences":[{"sContent":"...it may be time-consuming and troublesome to search information online...","sourceInfo":{"paper":"第二套","level":"CET6","year":"2013.12","type":"写作题"}}],"desc":"真题例句"},"usphone":"'trʌblsəm","syno":{"synos":[{"pos":"adj","tran":"麻烦的；讨厌的；使人苦恼的","hwds":[{"w":"tight"},{"w":"evil"},{"w":"rank"},{"w":"unpleasant"}]}],"desc":"同近"},"ukphone":"'trʌb(ə)ls(ə)m","ukspeech":"troublesome&type=1","star":0,"phone":"'trʌblsəm","speech":"troublesome","relWord":{"desc":"同根","rels":[{"pos":"n","words":[{"hwd":"trouble","tran":"麻烦；烦恼；故障；动乱"},{"hwd":"troublemaker","tran":"捣乱者，闹事者；惹麻烦的人"},{"hwd":"troubleshooter","tran":"故障检修工；解决纠纷者；解决麻烦问题的能手"}]},{"pos":"vi","words":[{"hwd":"trouble","tran":"费心，烦恼"}]},{"pos":"vt","words":[{"hwd":"trouble","tran":"麻烦；使烦恼；折磨"}]}]},"usspeech":"troublesome&type=2","trans":[{"tranCn":"困难的","descOther":"英释","pos":"adj","descCn":"中释","tranOther":"A troublesome situation or issue is full of complicated problems or difficulties."}]}}},"bookId":"CET6_2"}
