{"wordRank":9,"headWord":"Guinness","content":{"word":{"wordHead":"Guinness","wordId":"PEPGaoZhong_9_9","content":{"sentence":{"sentences":[{"sContent":"I have to confess I acquired this belief from the book Guinness World Records.","sCn":"我得说我是从《吉尼斯世界纪录》这本书里找到了这一信仰。"},{"sContent":"They have been married for seven years, but it took the Hallquists until this year to contact Guinness World Records.","sCn":"霍尔奎斯特夫妇已经结婚七年，但是直到今年他们才联系了吉尼斯世界纪录。"}],"desc":"例句"},"usphone":"'ɡinis","phrase":{"phrases":[{"pContent":"guinness world records","pCn":"吉尼斯世界记录"}],"desc":"短语"},"phone":"'ɡinis","speech":"guinness&type=3","usspeech":"guinness&type=3","trans":[{"tranCn":"吉尼斯","descCn":"中释"}]}}},"bookId":"PEPGaoZhong_9"}
