{"wordRank":1464,"headWord":"capsize","content":{"word":{"wordHead":"capsize","wordId":"Level8_2_1464","content":{"sentence":{"sentences":[{"sContent":"The sea got very rough and the boat capsized.","sCn":"海的风浪变得很大，船翻了。"}],"desc":"例句"},"usphone":"'kæpsaɪz","syno":{"synos":[{"pos":"vt","tran":"倾覆（特指船）；翻覆；弄翻","hwds":[{"w":"turn turtle"},{"w":"keel over"}]},{"pos":"vi","tran":"翻；倾覆；翻覆","hwds":[{"w":"tip"},{"w":"turn turtle"}]}],"desc":"同近"},"ukphone":"kæp'saɪz","ukspeech":"capsize&type=1","star":0,"phone":"kæp'saiz","speech":"capsize","usspeech":"capsize&type=2","trans":[{"tranCn":"倾覆（特指船）；翻覆；弄翻","descOther":"英释","descCn":"中释","pos":"v","tranOther":"if a boat capsizes, or if you capsize it, it turns over in the water"}]}}},"bookId":"Level8_2"}
