{"wordRank":777,"headWord":"litigant","content":{"word":{"wordHead":"litigant","wordId":"GMATluan_2_777","content":{"sentence":{"sentences":[{"sContent":"Touching the case, I suggest that we should go to ask the litigant.","sContent_eng":"Touching the case, I suggest that we should go to ask the <b>litigant</b>.","sSpeech":"Touching+the+case%2C+I+suggest+that+we+should+go+to+ask+the+litigant.&le=eng","sCn":"关于这个案子，我建议我们去问问当事人。"},{"sContent":"How can I as a private litigant seek redress for defamation that ruins my business?","sContent_eng":"How can I as a private <b>litigant</b> seek redress for defamation that ruins my business?","sSpeech":"How+can+I+as+a+private+litigant+seek+redress+for+defamation+that+ruins+my+business%3F&le=eng","sCn":"做为私人诉讼当事人，我怎么对毁了我的事业的诽谤寻求补救呢？"}],"desc":"例句"},"usphone":"'lɪtɪɡənt","syno":{"synos":[{"pos":"adj","tran":"诉讼的","hwds":[{"w":"contentious"}]}],"desc":"同近"},"ukphone":"'lɪtɪg(ə)nt","ukspeech":"litigant&type=1","star":0,"phone":"'litiɡənt","speech":"litigant","remMethod":{"val":" litig(打官司) + ant → 打官司的人 → 诉讼人","desc":"记忆"},"relWord":{"rels":[{"pos":"adj","words":[{"hwd":"litigious","tran":" 好诉讼的；好争论的"}]},{"pos":"n","words":[{"hwd":"litigation","tran":" 诉讼；起诉"},{"hwd":"litigator","tran":" 诉讼律师；诉讼人"}]},{"pos":"vi","words":[{"hwd":"litigate","tran":" 对簿法庭"}]},{"pos":"vt","words":[{"hwd":"litigate","tran":" 在法庭相争；提出诉讼"}]}],"desc":"同根"},"usspeech":"litigant&type=2","trans":[{"tranCn":"诉讼当事人","descOther":"英释","descCn":"中释","pos":"n","tranOther":"someone who is making a claim against someone or defending themselves against a claim in a court of law"},{"tranCn":"诉讼的","descCn":"中释","pos":"adj"}]}}},"bookId":"GMATluan_2"}
