{"wordRank":1852,"headWord":"amnesia","content":{"word":{"wordHead":"amnesia","wordId":"TOEFL_2_1852","content":{"sentence":{"sentences":[{"sContent":"We tend to think that a person who is a complete victim of amnesia is still the same person as before.","sContent_eng":"We tend to think that a person who is a complete victim of <b>amnesia</b> is still the same person as before.","sSpeech":"We+tend+to+think+that+a+person+who+is+a+complete+victim+of+amnesia+is+still+the+same+person+as+before.&le=eng","sCn":"我们倾向于认为，一个彻底的健忘症患者，他与以前没有患病时仍然是同一个人。"}],"desc":"例句"},"usphone":"æm'niʒə","ukphone":"æm'niːzɪə","ukspeech":"amnesia&type=1","star":0,"phrase":{"phrases":[{"pContent":"retrograde amnesia","pCn":"逆行性遗忘"}],"desc":"短语"},"phone":"æm'ni:zjə","speech":"amnesia","relWord":{"rels":[{"pos":"adj","words":[{"hwd":"amnesic","tran":" 遗忘的；失去记忆的"},{"hwd":"amnestic","tran":" 遗忘的；记忆缺失的（等于amnesiac）"}]}],"desc":"同根"},"usspeech":"amnesia&type=2","trans":[{"tranCn":"健忘症","descCn":"中释","pos":"n"}]}}},"bookId":"TOEFL_2"}
