{"wordRank":5385,"headWord":"assortment","content":{"word":{"wordHead":"assortment","wordId":"TOEFL_2_5385","content":{"usphone":"ə'sɔrtmənt","syno":{"synos":[{"pos":"n","tran":"[生物]分类；混合物","hwds":[{"w":"classification"},{"w":"category"},{"w":"mixture"},{"w":"hybrid"},{"w":"mix"}]}],"desc":"同近"},"ukphone":"ə'sɔːtm(ə)nt","ukspeech":"assortment&type=1","star":0,"phone":"ə'sɔ:tmənt","speech":"assortment","relWord":{"rels":[{"pos":"adj","words":[{"hwd":"assorted","tran":" 组合的；各种各样的；混杂的"}]},{"pos":"v","words":[{"hwd":"assorted","tran":" 把…分等级；把…归为一类（assort的过去分词）"}]},{"pos":"vi","words":[{"hwd":"assort","tran":" 协调；交往"}]},{"pos":"vt","words":[{"hwd":"assort","tran":" 把…分级；把…归为一类"}]}],"desc":"同根"},"usspeech":"assortment&type=2","trans":[{"tranCn":"分类,混合物","descCn":"中释","pos":"n"}]}}},"bookId":"TOEFL_2"}
