{"wordRank":1907,"headWord":"intrigue","content":{"word":{"wordHead":"intrigue","wordId":"TOEFL_2_1907","content":{"sentence":{"sentences":[{"sContent":"Other people’s houses always intrigued her.","sCn":"别人的房子总令她好奇。"}],"desc":"例句"},"usphone":"'ɪn'triɡ","syno":{"synos":[{"pos":"n","tran":"阴谋；诡计；复杂的事；私通","hwds":[{"w":"scheme"},{"w":"designing"},{"w":"fraud"},{"w":"plot"},{"w":"conspiracy"}]},{"pos":"vi","tran":"私通；密谋","hwds":[{"w":"plot"},{"w":"collogue"}]}],"desc":"同近"},"ukphone":"ɪn'triːg","ukspeech":"intrigue&type=1","star":0,"phone":"in'tri:ɡ, 'in-","speech":"intrigue","remMethod":{"val":" in(进入) + trig(=tric小障碍物) + ue → 在里面放小障碍物 → 搞阴谋诡计 → 阴谋","desc":"记忆"},"relWord":{"rels":[{"pos":"adj","words":[{"hwd":"intriguing","tran":" 有趣的；迷人的"}]},{"pos":"n","words":[{"hwd":"intriguer","tran":" [法] 密谋者，阴谋者；私通者"}]},{"pos":"v","words":[{"hwd":"intriguing","tran":" 引起…的兴趣；策划阴谋；私通（intrigue的ing形式）"}]}],"desc":"同根"},"usspeech":"intrigue&type=2","trans":[{"tranCn":"激起兴趣,耍阴谋","descOther":"英释","descCn":"中释","pos":"v","tranOther":"if something intrigues you, it interests you a lot because it seems strange or mysterious"},{"tranCn":"阴谋，密谋","descOther":"英释","descCn":"中释","pos":"n","tranOther":"the making of secret plans to harm someone or make them lose their position of power, or a plan of this kind"}]}}},"bookId":"TOEFL_2"}
