{"wordRank":7056,"headWord":"lightweight","content":{"word":{"wordHead":"lightweight","wordId":"TOEFL_2_7056","content":{"sentence":{"sentences":[{"sContent":"an intellectual lightweight","sCn":"智力平庸的人"}],"desc":"例句"},"usphone":"'laɪtwet","syno":{"synos":[{"pos":"n","tran":"轻量级选手；无足轻重的人","hwds":[{"w":"flyweight"},{"w":"small fry"}]}],"desc":"同近"},"ukphone":"'laɪtweɪt","ukspeech":"lightweight&type=1","star":0,"phrase":{"phrases":[{"pContent":"lightweight aggregate","pCn":"轻骨料；轻砂石"},{"pContent":"lightweight aggregate concrete","pCn":"轻骨料混凝土；轻质集料混凝土"},{"pContent":"lightweight concrete","pCn":"轻质混凝土"},{"pContent":"lightweight construction","pCn":"轻型结构；轻量构造"}],"desc":"短语"},"phone":"'laitweit","speech":"lightweight","usspeech":"lightweight&type=2","trans":[{"tranCn":"轻量级选手, 不能胜任者","descOther":"英释","descCn":"中释","pos":"n","tranOther":"a boxer who weighs less than 61.24 kilograms, and who is heavier than a featherweight but lighter than a welterweight"}]}}},"bookId":"TOEFL_2"}
