{"wordRank":1511,"headWord":"maker","content":{"word":{"wordHead":"maker","wordId":"TOEFL_2_1511","content":{"sentence":{"sentences":[{"sContent":"a leading Japanese computer maker","sCn":"日本一家主要的计算机生产商"}],"desc":"例句"},"usphone":"'mekɚ","syno":{"synos":[{"pos":"n","tran":"[经]制造者；造物主；出期票人","hwds":[{"w":"Creator"},{"w":"fabricant"}]}],"desc":"同近"},"ukphone":"'meɪkə","ukspeech":"maker&type=1","star":0,"phrase":{"phrases":[{"pContent":"decision maker","pCn":"决策人"},{"pContent":"coffee maker","pCn":"n. 咖啡壶；咖啡机"},{"pContent":"film maker","pCn":"n. 电影导演；电影制作人"},{"pContent":"market maker","pCn":"准备买卖未上市股票的经纪人；[经]从事欧洲债券二级市场交易的银行"},{"pContent":"policy maker","pCn":"政策制定者，决策者"},{"pContent":"ice maker","pCn":"制冰机，制冰器；制冰装置"},{"pContent":"trouble maker","pCn":"惹事生非的人"},{"pContent":"bread maker","pCn":"面包机"},{"pContent":"tool maker","pCn":"模具钳工；工具工人"},{"pContent":"pattern maker","pCn":"模型技工"},{"pContent":"money maker","pCn":"会赚钱的人"}],"desc":"短语"},"phone":"'meikə","speech":"maker","relWord":{"rels":[{"pos":"adj","words":[{"hwd":"made","tran":" 成功的；创造的"},{"hwd":"makable","tran":" 可制作的；可标记的"}]},{"pos":"n","words":[{"hwd":"make","tran":" 制造；构造；性情"},{"hwd":"making","tran":" 发展；制造；形成"}]},{"pos":"v","words":[{"hwd":"made","tran":" 做，使，安排（make的过去式和过去分词）"},{"hwd":"making","tran":" 制作（make的现在分词）"}]},{"pos":"vi","words":[{"hwd":"make","tran":" 开始；前进；增大；被制造"}]},{"pos":"vt","words":[{"hwd":"make","tran":" 使得；进行；布置，准备，整理；制造；认为；获得；形成；安排；引起；构成"}]}],"desc":"同根"},"usspeech":"maker&type=2","trans":[{"tranCn":"制造者","descOther":"英释","descCn":"中释","pos":"n","tranOther":"a person or company that makes a particular type of goods"}]}}},"bookId":"TOEFL_2"}
