{"wordRank":2169,"headWord":"niche","content":{"word":{"wordHead":"niche","wordId":"TOEFL_2_2169","content":{"sentence":{"sentences":[{"sContent":"Amanda soon found her niche at the club.","sCn":"阿曼达很快就在俱乐部里找到了一份理想的工作。"}],"desc":"例句"},"usphone":"niʃ","syno":{"synos":[{"pos":"n","tran":"[建]壁龛；合适的职业","hwds":[{"w":"habitacle"},{"w":"alcove"}]}],"desc":"同近"},"ukphone":"niːʃ; nɪtʃ","ukspeech":"niche&type=1","star":0,"phrase":{"phrases":[{"pContent":"niche market","pCn":"瞄准机会的市场；缝隙市场"},{"pContent":"market niche","pCn":"市场利基；市场定位；市场补缺基点；市场补缺者"},{"pContent":"ecological niche","pCn":"生态位；生态龛位；小生境；生态区位"}],"desc":"短语"},"speech":"niche","remMethod":{"val":" nice(好的)中间加h → 比nice还多一点， 更好更合适 → 生态位","desc":"记忆"},"usspeech":"niche&type=2","trans":[{"tranCn":"壁龛,合适的职务(环境、位置等)","descOther":"英释","descCn":"中释","pos":"n","tranOther":"a hollow place in a wall, often made to hold a statue"}]}}},"bookId":"TOEFL_2"}
