{"wordRank":5003,"headWord":"tenfold","content":{"word":{"wordHead":"tenfold","wordId":"TOEFL_2_5003","content":{"sentence":{"sentences":[{"sContent":"Business has increased tenfold in the past two years.","sCn":"在过去两年里，业务扩展了十倍。"}],"desc":"例句"},"syno":{"synos":[{"pos":"adj","tran":"十倍的；十重的","hwds":[{"w":"decuple"}]},{"pos":"n","tran":"十倍","hwds":[{"w":"decuple"}]}],"desc":"同近"},"ukphone":"'tenfəʊld","ukspeech":"tenfold&type=1","star":0,"phone":"'tenfəuld","speech":"tenfold","trans":[{"tranCn":"十倍的 ad成十倍","descOther":"英释","descCn":"中释","pos":"adj","tranOther":"ten times as much or as many of something"}]}}},"bookId":"TOEFL_2"}
