{"wordRank":8885,"headWord":"tessellation","content":{"word":{"wordHead":"tessellation","wordId":"TOEFL_2_8885","content":{"syno":{"synos":[{"pos":"n","tran":"棋盘形布置；[建]棋盘花纹镶嵌；镶嵌式铺装；镶嵌细工；棋盘花纹","hwds":[{"w":"marquetry"},{"w":"buhl"}]}],"desc":"同近"},"star":0,"phone":",tesi'leiʃən","speech":"tessellation","relWord":{"rels":[{"pos":"adj","words":[{"hwd":"tessellate","tran":" 镶嵌细工的；嵌成花纹的"},{"hwd":"tessellated","tran":" 镶嵌成棋盘花纹的；[动] 棋盘格形的；[植] 具方格斑纹的"}]},{"pos":"n","words":[{"hwd":"tessella","tran":" [建] 小块镶嵌大理石，镶嵌地砖；特塞拉"},{"hwd":"tessera","tran":" 镶嵌物；入场券；纪念品"}]},{"pos":"v","words":[{"hwd":"tessellated","tran":" 用小块大理石铺路面；完全嵌合（动词tessellate的过去式和过去分词）"}]},{"pos":"vi","words":[{"hwd":"tessellate","tran":" 完全嵌合"}]},{"pos":"vt","words":[{"hwd":"tessellate","tran":" 把…镶装花纹"}]}],"desc":"同根"},"trans":[{"tranCn":"棋盘形嵌石饰","descOther":"英释","descCn":"中释","pos":"n","tranOther":"the act of tessellating "}]}}},"bookId":"TOEFL_2"}
