{"wordRank":846,"headWord":"Washington","content":{"word":{"wordHead":"Washington","wordId":"TOEFL_2_846","content":{"sentence":{"sentences":[{"sContent":"What time does the train get into Washington?","sContent_eng":"What time does the train get into <b>Washington</b>?","sSpeech":"What+time+does+the+train+get+into+Washington%3F&le=eng","sCn":"这趟火车什么时间到达华盛顿?"},{"sContent":"The President departed from Washington today.","sContent_eng":"The President departed from <b>Washington</b> today.","sSpeech":"The+President+departed+from+Washington+today.&le=eng","sCn":"总统今天从华盛顿出发。"},{"sContent":"The library was modelled after the library of Congress of Washington.","sContent_eng":"The library was modelled after the library of Congress of <b>Washington</b>.","sSpeech":"The+library+was+modelled+after+the+library+of+Congress+of+Washington.&le=eng","sCn":"这个图书馆是按华盛顿国会图书馆的式样设计建造的。"}],"desc":"例句"},"usphone":"ˈwɑʃɪŋtən","ukphone":"ˈwɒʃɪŋtən","ukspeech":"Washington&type=1","star":0,"phrase":{"phrases":[{"pContent":"george washington","pCn":"乔治·华盛顿（美国第一位总统）"},{"pContent":"washington state","pCn":"华盛顿州（位于美国西北部）"},{"pContent":"washington post","pCn":"华盛顿邮报"},{"pContent":"university of washington","pCn":"华盛顿大学"},{"pContent":"washington dc","pCn":"华盛顿（特区）；华盛顿哥伦比亚特区"},{"pContent":"washington monument","pCn":"华盛顿纪念碑"},{"pContent":"washington mutual","pCn":"华盛顿互惠银行（公司）；华盛顿共同基金"},{"pContent":"denzel washington","pCn":"丹泽尔·华盛顿（美国黑人演员）"}],"desc":"短语"},"phone":"'wɔʃiŋtən","speech":"Washington","usspeech":"Washington&type=2","trans":[{"tranCn":"华盛顿","descCn":"中释","pos":"n"}]}}},"bookId":"TOEFL_2"}
