{"wordRank":228,"headWord":"Big Bang","content":{"word":{"wordHead":"Big Bang","wordId":"PEPGaoZhong_3_228","content":{"sentence":{"sentences":[{"sContent":"We have a lot of energy in a small space, like you did at the Big Bang.","sCn":"的确，正如像宇宙大爆炸一样，我们在一个小空间里面有巨大的能量。"},{"sContent":"A \"quark-gluon plasma\" can be created if the collisions are energetic enough, a state of matter that existed during the high-energy conditions just after the Big Bang.","sCn":"如果对撞的能量足够大，就可能制造出一种“夸克——胶子等离子体”，这是在宇宙大爆炸之后的高能环境下存在的一种物质状态。"}],"desc":"例句"},"speech":"Big+Bang","trans":[{"tranCn":"宇宙大爆炸；创世大爆炸","descOther":"英释","descCn":"中释","tranOther":"the single large explosion that some scientists suggest created the universe"}]}}},"bookId":"PEPGaoZhong_3"}
