{"wordRank":1122,"headWord":"setback","content":{"word":{"wordHead":"setback","wordId":"BEC_3_1122","content":{"sentence":{"sentences":[{"sContent":"The team’s hopes of playing in Europe suffered a setback last night.","sCn":"球队赴欧洲参加比赛的希望昨晚遇到了阻碍。"}],"desc":"例句"},"usphone":"'sɛtbæk","syno":{"synos":[{"pos":"n","tran":"挫折；退步；逆流","hwds":[{"w":"frustration"},{"w":"clawback"}]}],"desc":"同近"},"ukphone":"'setbæk","ukspeech":"setback&type=1","remMethod":{"val":" set(设置) + back(往后的) → 设置障碍让其往后倒退 → 倒退","desc":"记忆"},"usspeech":"setback&type=2","trans":[{"tranCn":" 挫折， 倒退， 失败","descOther":"英释","pos":"n","descCn":"中释","tranOther":"a problem that delays or prevents progress, or makes things worse than they were"}]}}},"bookId":"BEC_3"}
