{"wordRank":132,"headWord":"align","content":{"word":{"wordHead":"align","wordId":"BEC_2_132","content":{"sentence":{"sentences":[{"sContent":"The desks were neatly aligned in rows.","sCn":"书桌一行行排得整整齐齐。"},{"sContent":"Make sure that all the holes align.","sCn":"确保所有的洞眼成一条直线。"}],"desc":"例句"},"usphone":"ə'laɪn","ukspeech":"align&type=1","star":0,"usspeech":"align&type=2","syno":{"synos":[{"pos":"vt","tran":"使结盟；使成一行；匹配","hwds":[{"w":"to match"}]},{"pos":"vi","tran":"排列；排成一行","hwds":[{"w":"arrange"},{"w":"form"}]}],"desc":"同近"},"ukphone":"ə'laɪn","phrase":{"phrases":[{"pContent":"align with","pCn":"v. 与……结盟"}],"desc":"短语"},"phone":"ə'lain","speech":"align","remMethod":{"val":" 排成(align)一条线(a line)","desc":"记忆"},"relWord":{"rels":[{"pos":"n","words":[{"hwd":"alignment","tran":" 队列，成直线；校准；结盟"}]}],"desc":"同根"},"trans":[{"tranCn":"使结盟；使成一行；匹配","descOther":"英释","descCn":"中释","pos":"v","tranOther":"to arrange things so that they form a line or are parallel to each other, or to be in a position that forms a line etc"}]}}},"bookId":"BEC_2"}
