{"wordRank":610,"headWord":"figurehead","content":{"word":{"wordHead":"figurehead","wordId":"Level8_1_610","content":{"sentence":{"sentences":[{"sContent":"The president will be little more than a figurehead.","sCn":"主席将只不过是个傀儡而已。"}],"desc":"例句"},"usphone":"'fɪgjɚ'hɛd","ukphone":"'fiɡəhed","ukspeech":"figurehead&type=1","star":0,"phone":"'fiɡəhed","speech":"figurehead","relWord":{"rels":[{"pos":"n","words":[{"hwd":"figuration","tran":" 成形；外形；定形；比喻表达法；图案装饰法"}]}],"desc":"同根"},"usspeech":"figurehead&type=2","trans":[{"tranCn":"傀儡","descOther":"英释","descCn":"中释","pos":"n","tranOther":"If someone is the figurehead of an organization or movement, they are recognized as being its leader, although they have little real power"}]}}},"bookId":"Level8_1"}
