{"wordRank":217,"headWord":"spokesman","content":{"word":{"wordHead":"spokesman","wordId":"KaoYanluan_1_217","content":{"sentence":{"sentences":[{"sContent":"a White House spokesman","sCn":"白宫发言人"}],"desc":"例句"},"usphone":"'spoksmən","syno":{"synos":[{"pos":"n","tran":"发言人；代言人","hwds":[{"w":"prolocutor"},{"w":"public speaker"}]}],"desc":"同近"},"ukphone":"'spəʊksmən","ukspeech":"spokesman&type=1","star":0,"phone":"'spəuksmən","speech":"spokesman","usspeech":"spokesman&type=2","trans":[{"tranCn":"发言人","descOther":"英释","pos":"n","descCn":"中释","tranOther":"a man who has been chosen to speak officially for a group, organization, or government"}]}}},"bookId":"KaoYanluan_1"}
