{"wordRank":3487,"headWord":"physicist","content":{"word":{"wordHead":"physicist","wordId":"KaoYan_2_3487","content":{"sentence":{"sentences":[{"sContent":"...a nuclear physicist.","sCn":"…一位核物理学家。"}],"desc":"例句"},"usphone":"'fɪzɪsɪst","ukspeech":"physicist&type=1","star":0,"usspeech":"physicist&type=2","syno":{"synos":[{"pos":"n","tran":"物理学家；唯物论者","hwds":[{"w":"physical scientist"}]}],"desc":"同近"},"ukphone":"'fɪzɪsɪst","phrase":{"phrases":[{"pContent":"nuclear physicist","pCn":"核物理学家"}],"desc":"短语"},"phone":"'fizisist","speech":"physicist","remMethod":{"val":" physi(自然)+c+ist(从事某职业的人)→研究大自然的人→物理学家","desc":"记忆"},"relWord":{"rels":[{"pos":"adj","words":[{"hwd":"physical","tran":" [物] 物理的；身体的；物质的"},{"hwd":"physiological","tran":" 生理学的，生理的"},{"hwd":"physicochemical","tran":" 物理化学的"},{"hwd":"physiotherapeutic","tran":" 物理疗法的；理疗的"}]},{"pos":"adv","words":[{"hwd":"physiologically","tran":" 生理学方面"}]},{"pos":"n","words":[{"hwd":"physical","tran":" 体格检查"},{"hwd":"physics","tran":" 物理学；物理现象"},{"hwd":"physiology","tran":" 生理学；生理机能"},{"hwd":"physic","tran":" 医学；药品（特指泻药）"},{"hwd":"physiatrics","tran":" 物理疗法"},{"hwd":"physicalism","tran":" 物理主义"},{"hwd":"physiography","tran":" 地文学，地相学；自然地理学；自然现象志"}]},{"pos":"vt","words":[{"hwd":"physic","tran":" 给…服药；治愈"}]}],"desc":"同根"},"trans":[{"tranCn":"物理学家；唯物论者","descOther":"英释","descCn":"中释","pos":"n","tranOther":"a scientist who has special knowledge and training in  physics "}]}}},"bookId":"KaoYan_2"}
