{"wordRank":482,"headWord":"adhere","content":{"word":{"wordHead":"adhere","wordId":"KaoYan_1_482","content":{"sentence":{"sentences":[{"sContent":"All members of the association adhere to a strict code of practice.","sCn":"所有该协会的成员都遵守严格的业务守则。"}],"desc":"例句"},"usphone":"əd'hɪr","syno":{"synos":[{"pos":"vi","tran":"坚持；依附；粘着；追随","hwds":[{"w":"stay"},{"w":"stand on"}]}],"desc":"同近"},"ukphone":"əd'hɪə","ukspeech":"adhere&type=1","star":0,"phone":"əd'hiə","speech":"adhere","remMethod":{"val":" ad(表加强)+her(黏附)+e→黏附","desc":"记忆"},"relWord":{"rels":[{"pos":"adj","words":[{"hwd":"adherent","tran":" 附着的；粘着的"}]},{"pos":"n","words":[{"hwd":"adherence","tran":" 坚持；依附；忠诚"},{"hwd":"adherent","tran":" 信徒；追随者"}]}],"desc":"同根"},"usspeech":"adhere&type=2","trans":[{"tranCn":"(to)粘着；坚持，遵守；依附，追随","descOther":"英释","descCn":"中释","pos":"v","tranOther":"to stick firmly to something"}]}}},"bookId":"KaoYan_1"}
