{"wordRank":1636,"headWord":"gullible","content":{"word":{"wordHead":"gullible","wordId":"Level4_2_1636","content":{"sentence":{"sentences":[{"sContent":"Plastic replicas of the Greek pottery are sold to gullible tourists.","sCn":"仿古希腊陶器的塑料复制品被卖给易受骗的游客。"}],"desc":"例句"},"usphone":"'ɡʌləbl","syno":{"synos":[{"pos":"adj","tran":"易受骗的；轻信的","hwds":[{"w":"naive"},{"w":"credulous"}]}],"desc":"同近"},"ukphone":"'gʌlɪb(ə)l","ukspeech":"gullible&type=1","star":0,"phone":"'ɡʌləbl","speech":"gullible","relWord":{"rels":[{"pos":"n","words":[{"hwd":"gull","tran":" [鸟] 鸥；笨人；易受骗之人"},{"hwd":"gullibility","tran":" 轻信；易受骗"}]},{"pos":"vt","words":[{"hwd":"gull","tran":" 骗；欺诈"}]}],"desc":"同根"},"usspeech":"gullible&type=2","trans":[{"tranCn":"易受骗的；轻信的","descOther":"英释","descCn":"中释","pos":"adj","tranOther":"too ready to believe what other people tell you, so that you are easily tricked"}]}}},"bookId":"Level4_2"}
