{"wordRank":1637,"headWord":"gulp","content":{"word":{"wordHead":"gulp","wordId":"Level4_2_1637","content":{"sentence":{"sentences":[{"sContent":"She gulped down her breakfast and ran for the bus.","sCn":"她狼吞虎咽地吃完早饭，跑去赶公交车了。"}],"desc":"例句"},"usphone":"ɡʌlp","syno":{"synos":[{"pos":"vt","tran":"狼吞虎咽地吃；大口地吸","hwds":[{"w":"wolf"}]},{"pos":"vi","tran":"哽住；喘不过气","hwds":[{"w":"lose one's breath"}]},{"pos":"n","tran":"一大口（尤指液体）；吞咽","hwds":[{"w":"deglutition"},{"w":"swallowing"}]}],"desc":"同近"},"ukphone":"gʌlp","ukspeech":"gulp&type=1","star":0,"phrase":{"phrases":[{"pContent":"gulp down","pCn":"狼吞虎咽地吃；忍住"}],"desc":"短语"},"phone":"ɡʌlp","speech":"gulp","relWord":{"rels":[{"pos":"n","words":[{"hwd":"gulper","tran":" 囊咽鱼"}]}],"desc":"同根"},"usspeech":"gulp&type=2","trans":[{"tranCn":"狼吞虎咽地吃；大口地吸","descOther":"英释","descCn":"中释","pos":"v","tranOther":"to swallow large quantities of food or drink quickly"},{"tranCn":"一大口（尤指液体）；吞咽","descOther":"英释","descCn":"中释","pos":"n","tranOther":"a large amount of something that you swallow quickly, or the action of swallowing"}]}}},"bookId":"Level4_2"}
