{"wordRank":2721,"headWord":"prose","content":{"word":{"wordHead":"prose","wordId":"Level4_2_2721","content":{"sentence":{"sentences":[{"sContent":"Shute's prose is stark and chillingly unsentimental.","sCn":"舒特的散文刻板而冷峻。"}],"desc":"例句"},"usphone":"proz","syno":{"synos":[{"pos":"n","tran":"散文；单调","hwds":[{"w":"essay"},{"w":"monotony"}]},{"pos":"adj","tran":"散文的；平凡的；乏味的","hwds":[{"w":"ordinary"},{"w":"stock"},{"w":"stupid"}]}],"desc":"同近"},"ukphone":"prəʊz","ukspeech":"prose&type=1","star":0,"phrase":{"phrases":[{"pContent":"prose poem","pCn":"n. 散文诗"},{"pContent":"descriptive prose","pCn":"描写性散文"}],"desc":"短语"},"phone":"prəuz","speech":"prose","relWord":{"rels":[{"pos":"adj","words":[{"hwd":"prosaic","tran":" 平凡的，乏味的；散文体的"},{"hwd":"prosy","tran":" 散文的；散文体的；单调的"}]},{"pos":"adv","words":[{"hwd":"prosaically","tran":" 平凡地；散文式地"},{"hwd":"prosily","tran":" 无趣味地；用散文体地"}]},{"pos":"n","words":[{"hwd":"prosiness","tran":" 单调，平凡；散文体"}]}],"desc":"同根"},"usspeech":"prose&type=2","trans":[{"tranCn":"散文；单调","descOther":"英释","descCn":"中释","pos":"n","tranOther":"language in its usual form, as opposed to poetry"},{"tranCn":"散文的；平凡的；乏味的","descCn":"中释","pos":"adj"},{"tranCn":"写散文；乏味地讲话","descCn":"中释","pos":"vi"},{"tranCn":"把…写成散文","descCn":"中释","pos":"vt"}]}}},"bookId":"Level4_2"}
