{"wordRank":764,"headWord":"unified","content":{"word":{"wordHead":"unified","wordId":"CET6_1_764","content":{"sentence":{"sentences":[{"sContent":"a unified approach","sCn":"统一的方法"},{"sContent":"a unified market","sCn":"统一的市场"}],"desc":"例句"},"usphone":"'ju:nifaid","ukspeech":"unified&type=1","star":0,"usspeech":"unified&type=2","syno":{"synos":[{"pos":"adj","tran":"统一的；一致标准的","hwds":[{"w":"united"},{"w":"consolidated"}]},{"pos":"v","tran":"统一；使一致（unify的过去分词）","hwds":[{"w":"unitized"}]}],"desc":"同近"},"ukphone":"'ju:nɪfaɪd","phrase":{"phrases":[{"pContent":"unified management","pCn":"统一管理；统一经营"},{"pContent":"unified standards","pCn":"统一标准"},{"pContent":"unified examination","pCn":"统一试验；会考"},{"pContent":"unified brand","pCn":"统一商标；统一牌号"}],"desc":"短语"},"phone":"'ju:nifaid","speech":"unified","remMethod":{"val":" uni(单一) ＋ fy(使…) → 统一","desc":"记忆"},"relWord":{"rels":[{"pos":"vt","words":[{"hwd":"unify","tran":" 统一；使相同，使一致"}]}],"desc":"同根"},"trans":[{"tranCn":"统一的","descOther":"英释","descCn":"中释","pos":"adj","tranOther":"created from more than one part, group etc"}]}}},"bookId":"CET6_1"}
