{"wordRank":3403,"headWord":"artful","content":{"word":{"wordHead":"artful","wordId":"SAT_3_3403","content":{"sentence":{"sentences":[{"sContent":"artful tricks","sCn":"诡计"}],"desc":"例句"},"usphone":"'ɑrtfl","syno":{"synos":[{"pos":"adj","tran":"巧妙的；狡猾的；有技巧的；欺诈的","hwds":[{"w":"happy"},{"w":"designing"},{"w":"knowing"},{"w":"accomplished"},{"w":"smart"}]}],"desc":"同近"},"ukphone":"'ɑːtful","ukspeech":"artful&type=1","remMethod":{"val":" art (技巧) + ful (…的) → 有技巧的 → 巧妙的","desc":"记忆"},"relWord":{"rels":[{"pos":"adv","words":[{"hwd":"artfully","tran":" 巧妙地；狡诈地"}]},{"pos":"n","words":[{"hwd":"artfulness","tran":" 狡猾"}]}],"desc":"同根"},"usspeech":"artful&type=2","trans":[{"tranCn":" 巧妙的， 狡猾的","descOther":"英释","pos":"adj","descCn":"中释","tranOther":"clever at deceiving people"}]}}},"bookId":"SAT_3"}
