{"wordRank":5,"headWord":"scientific","content":{"word":{"wordHead":"scientific","wordId":"PEPGaoZhong_5_5","content":{"sentence":{"sentences":[{"sContent":"We believe in investing in scientific research.","sCn":"我们相信科学研究的投资价值。"},{"sContent":"the limits of scientific knowledge","sCn":"科学知识的极限"},{"sContent":"decisions based on scientific evidence","sCn":"根据科学证据作出的决定"},{"sContent":"the international scientific community (= scientists )","sCn":"国际科学界"}],"desc":"例句"},"usphone":",saɪən'tɪfɪk","syno":{"synos":[{"pos":"adj","tran":"科学的，系统的","hwds":[{"w":"systematic"}]}],"desc":"同近"},"ukphone":"saɪən'tɪfɪk","ukspeech":"scientific&type=1","phrase":{"phrases":[{"pContent":"scientific research","pCn":"科学研究"},{"pContent":"scientific management","pCn":"科学管理"},{"pContent":"scientific progress","pCn":"科学进展"},{"pContent":"scientific method","pCn":"科学方法"},{"pContent":"scientific knowledge","pCn":"科学知识"},{"pContent":"scientific socialism","pCn":"科学社会主义"},{"pContent":"scientific data","pCn":"科学数据；科学资料"},{"pContent":"scientific community","pCn":"科学界"},{"pContent":"scientific revolution","pCn":"科学革命"},{"pContent":"scientific discovery","pCn":"科学发现"},{"pContent":"scientific literature","pCn":"科学文献"},{"pContent":"scientific instrument","pCn":"科学仪表"},{"pContent":"scientific and technical information","pCn":"科技信息；科技情报资料；科学与技术情报"},{"pContent":"scientific name","pCn":"学名"},{"pContent":"scientific paper","pCn":"科学著作"},{"pContent":"scientific communication","pCn":"科学交流"},{"pContent":"scientific calculator","pCn":"科学用计算器"},{"pContent":"scientific applications","pCn":"科学应用"},{"pContent":"scientific researcher","pCn":"科学研究人员"},{"pContent":"scientific english","pCn":"科技英语；专业英语"}],"desc":"短语"},"relWord":{"desc":"同根","rels":[{"pos":"adv","words":[{"hwd":"scientifically","tran":"系统地；合乎科学地；学问上"}]},{"pos":"n","words":[{"hwd":"science","tran":"科学；技术；学科；理科"},{"hwd":"scientist","tran":"科学家"}]}]},"remMethod":{"val":"来自science(n. 科学)","desc":"记忆"},"usspeech":"scientific&type=2","trans":[{"tranCn":"科学的","descOther":"英释","pos":"adj","descCn":"中释","tranOther":"about or related to science, or using its methods"}]}}},"bookId":"PEPGaoZhong_5"}
